[
  {
    "id": 1,
    "title": "Lợi Ích Của Bảo Hiểm Nhân Thọ Trong Kế Hoạch Tài Chính",
    "slug": "loi-ich-bao-hiem-nhan-tho-trong-ke-hoach-tai-chinh",
    "excerpt": "Khám phá lý do tại sao bảo hiểm nhân thọ đóng vai trò quan trọng trong việc bảo vệ tài chính của bạn.",
    "content": "<p>Bảo hiểm nhân thọ không chỉ bảo vệ gia đình bạn khi có rủi ro mà còn giúp bạn lên kế hoạch tiết kiệm dài hạn.</p>",
    "published_at": "2024-10-01",
    "author": "Nguyễn Văn A",
    "tags": ["bảo hiểm", "tài chính", "nhân thọ"],
    "thumbnails": [
      "/assets/images/posts/life1.jpg",
      "/assets/images/posts/life2.jpg",
      "/assets/images/posts/life3.jpg",
      "/assets/images/posts/life4.jpg"
    ],
    "meta": {
      "meta_title": "Lợi Ích Của Bảo Hiểm Nhân Thọ Trong Kế Hoạch Tài Chính - Tư Vấn Chuyên Nghiệp",
      "meta_description": "Tìm hiểu vai trò và lợi ích của bảo hiểm nhân thọ trong việc bảo vệ tài chính và kế hoạch dài hạn của bạn.",
      "meta_keywords": "bảo hiểm nhân thọ, tài chính cá nhân, tư vấn bảo hiểm"
    }
  },
  {
    "id": 2,
    "title": "Cách Lựa Chọn Gói Bảo Hiểm Sức Khỏe Phù Hợp",
    "slug": "cach-lua-chon-goi-bao-hiem-suc-khoe-phu-hop",
    "excerpt": "Hướng dẫn từng bước giúp bạn chọn gói bảo hiểm sức khỏe tối ưu.",
    "content": "<p>Để chọn được bảo hiểm sức khỏe phù hợp, bạn cần cân nhắc ngân sách, quyền lợi và các điều khoản loại trừ.</p>",
    "published_at": "2024-10-02",
    "author": "Trần Thị B",
    "tags": ["bảo hiểm sức khỏe"],
    "thumbnails": [
      "/assets/images/posts/health1.jpg",
      "/assets/images/posts/health2.jpg",
      "/assets/images/posts/health3.jpg",
      "/assets/images/posts/health4.jpg"
    ],
    "meta": {
      "meta_title": "Hướng Dẫn Chọn Bảo Hiểm Sức Khỏe Phù Hợp - Bảo Vệ Gia Đình",
      "meta_description": "Bài viết hướng dẫn chi tiết cách lựa chọn gói bảo hiểm sức khỏe chất lượng với chi phí hợp lý.",
      "meta_keywords": "bảo hiểm sức khỏe, lựa chọn bảo hiểm, tư vấn sức khỏe"
    }
  },
  {
    "id": 3,
    "title": "Những Điều Cần Biết Về Bảo Hiểm Du Lịch Quốc Tế",
    "slug": "nhung-dieu-can-biet-bao-hiem-du-lich-quoc-te",
    "excerpt": "Tìm hiểu các quyền lợi và lưu ý quan trọng khi mua bảo hiểm du lịch.",
    "content": "<p>Bảo hiểm du lịch giúp bạn an tâm trước rủi ro y tế, thất lạc hành lý và hủy chuyến bay.</p>",
    "published_at": "2024-10-03",
    "author": "Lê Văn C",
    "tags": ["bảo hiểm du lịch"],
    "thumbnails": [
      "/assets/images/posts/travel1.jpg",
      "/assets/images/posts/travel2.jpg",
      "/assets/images/posts/travel3.jpg",
      "/assets/images/posts/travel4.jpg"
    ],
    "meta": {
      "meta_title": "Những Điều Cần Biết Về Bảo Hiểm Du Lịch Quốc Tế - Kinh Nghiệm Du Lịch An Toàn",
      "meta_description": "Khám phá quyền lợi và mẹo chọn bảo hiểm du lịch quốc tế giúp chuyến đi của bạn an toàn hơn.",
      "meta_keywords": "bảo hiểm du lịch, bảo hiểm quốc tế, tư vấn du lịch"
    }
  },
  {
    "id": 4,
    "title": "Vai Trò Của Bảo Hiểm Mất Khả Năng Lao Động",
    "slug": "vai-tro-bao-hiem-mat-kha-nang-lao-dong",
    "excerpt": "Bảo hiểm mất khả năng lao động bảo vệ thu nhập khi bạn không thể làm việc.",
    "content": "<p>Loại bảo hiểm này chi trả trợ cấp hàng tháng giúp bạn duy trì cuộc sống ổn định.</p>",
    "published_at": "2024-10-04",
    "author": "Phạm Thị D",
    "tags": ["mất khả năng lao động"],
    "thumbnails": [
      "/assets/images/posts/disability1.jpg",
      "/assets/images/posts/disability2.jpg",
      "/assets/images/posts/disability3.jpg",
      "/assets/images/posts/disability4.jpg"
    ],
    "meta": {
      "meta_title": "Vai Trò Của Bảo Hiểm Mất Khả Năng Lao Động - Giải Pháp Bảo Vệ Thu Nhập",
      "meta_description": "Tìm hiểu lý do tại sao bảo hiểm mất khả năng lao động là cần thiết để bảo vệ thu nhập của bạn khi không thể lao động.",
      "meta_keywords": "bảo hiểm mất khả năng lao động, bảo vệ thu nhập"
    }
  },
  {
    "id": 5,
    "title": "10 Mẹo Để Tiết Kiệm Khi Mua Bảo Hiểm",
    "slug": "10-meo-tiet-kiem-khi-mua-bao-hiem",
    "excerpt": "Những bí quyết giúp bạn tối ưu chi phí mà vẫn được bảo vệ toàn diện.",
    "content": "<ul><li>So sánh nhiều gói bảo hiểm</li><li>Chọn mức khấu trừ hợp lý</li></ul>",
    "published_at": "2024-10-05",
    "author": "Nguyễn Văn E",
    "tags": ["mẹo bảo hiểm", "tiết kiệm"],
    "thumbnails": [
      "/assets/images/posts/save1.jpg",
      "/assets/images/posts/save2.jpg",
      "/assets/images/posts/save3.jpg",
      "/assets/images/posts/save4.jpg"
    ],
    "meta": {
      "meta_title": "10 Mẹo Tiết Kiệm Khi Mua Bảo Hiểm - Bí Quyết Hiệu Quả",
      "meta_description": "Khám phá 10 mẹo hữu ích giúp bạn tiết kiệm chi phí khi mua bảo hiểm mà vẫn đảm bảo quyền lợi.",
      "meta_keywords": "mẹo tiết kiệm bảo hiểm, chi phí bảo hiểm, kinh nghiệm mua bảo hiểm"
    }
  },
  {
    "id": 6,
    "title": "Bảo Hiểm Y Tế Gia Đình: Những Điều Nên Biết",
    "slug": "bao-hiem-y-te-gia-dinh-nhung-dieu-nen-biet",
    "excerpt": "Bảo vệ sức khỏe cả gia đình với những gói bảo hiểm y tế phù hợp.",
    "content": "<p>Bạn nên đánh giá nhu cầu khám chữa bệnh và khả năng tài chính trước khi lựa chọn.</p>",
    "published_at": "2024-10-06",
    "author": "Trần Thị F",
    "tags": ["bảo hiểm y tế"],
    "thumbnails": [
      "/assets/images/posts/family1.jpg",
      "/assets/images/posts/family2.jpg",
      "/assets/images/posts/family3.jpg",
      "/assets/images/posts/family4.jpg"
    ],
    "meta": {
      "meta_title": "Bảo Hiểm Y Tế Gia Đình - Hướng Dẫn Lựa Chọn Phù Hợp",
      "meta_description": "Tìm hiểu các tiêu chí để chọn gói bảo hiểm y tế gia đình tối ưu và tiết kiệm.",
      "meta_keywords": "bảo hiểm y tế gia đình, lựa chọn bảo hiểm, sức khỏe gia đình"
    }
  },
  {
    "id": 7,
    "title": "Bí Quyết Chọn Bảo Hiểm Xe Hơi Phù Hợp",
    "slug": "bi-quyet-chon-bao-hiem-xe-hoi-phu-hop",
    "excerpt": "Giúp bạn tránh rủi ro tài chính khi xe gặp sự cố.",
    "content": "<p>Kiểm tra kỹ điều khoản và các quyền lợi bổ sung trước khi ký hợp đồng.</p>",
    "published_at": "2024-10-07",
    "author": "Lê Văn G",
    "tags": ["bảo hiểm xe hơi"],
    "thumbnails": [
      "/assets/images/posts/car1.jpg",
      "/assets/images/posts/car2.jpg",
      "/assets/images/posts/car3.jpg",
      "/assets/images/posts/car4.jpg"
    ],
    "meta": {
      "meta_title": "Bí Quyết Chọn Bảo Hiểm Xe Hơi - An Tâm Mọi Hành Trình",
      "meta_description": "Hướng dẫn cách chọn bảo hiểm xe hơi giúp bạn yên tâm khi di chuyển.",
      "meta_keywords": "bảo hiểm xe hơi, chọn bảo hiểm xe, bảo vệ xe"
    }
  },
  {
    "id": 8,
    "title": "Những Quyền Lợi Quan Trọng Của Bảo Hiểm Sức Khỏe",
    "slug": "quyen-loi-quan-trong-cua-bao-hiem-suc-khoe",
    "excerpt": "Tìm hiểu các quyền lợi nổi bật giúp bạn bảo vệ sức khỏe toàn diện.",
    "content": "<p>Chi trả viện phí, hỗ trợ chi phí phẫu thuật và khám chữa bệnh định kỳ.</p>",
    "published_at": "2024-10-08",
    "author": "Phạm Thị H",
    "tags": ["quyền lợi bảo hiểm"],
    "thumbnails": [
      "/assets/images/posts/benefit1.jpg",
      "/assets/images/posts/benefit2.jpg",
      "/assets/images/posts/benefit3.jpg",
      "/assets/images/posts/benefit4.jpg"
    ],
    "meta": {
      "meta_title": "Quyền Lợi Quan Trọng Của Bảo Hiểm Sức Khỏe - Thông Tin Chi Tiết",
      "meta_description": "Khám phá các quyền lợi chính mà bảo hiểm sức khỏe mang lại cho bạn.",
      "meta_keywords": "quyền lợi bảo hiểm sức khỏe, bảo hiểm y tế, chăm sóc sức khỏe"
    }
  },
  {
    "id": 9,
    "title": "Lợi Ích Của Bảo Hiểm Nhà Ở",
    "slug": "loi-ich-bao-hiem-nha-o",
    "excerpt": "Bảo vệ ngôi nhà của bạn khỏi các rủi ro bất ngờ.",
    "content": "<p>Bảo hiểm nhà ở chi trả thiệt hại do cháy nổ, thiên tai hoặc trộm cắp.</p>",
    "published_at": "2024-10-09",
    "author": "Nguyễn Văn I",
    "tags": ["bảo hiểm nhà"],
    "thumbnails": [
      "/assets/images/posts/home1.jpg",
      "/assets/images/posts/home2.jpg",
      "/assets/images/posts/home3.jpg",
      "/assets/images/posts/home4.jpg"
    ],
    "meta": {
      "meta_title": "Lợi Ích Của Bảo Hiểm Nhà Ở - Bảo Vệ Tài Sản",
      "meta_description": "Tìm hiểu lý do tại sao bảo hiểm nhà ở giúp bạn yên tâm hơn trước mọi rủi ro.",
      "meta_keywords": "bảo hiểm nhà ở, bảo vệ nhà, tài sản gia đình"
    }
  },
  {
    "id": 10,
    "title": "Hướng Dẫn Chi Tiết Về Bảo Hiểm Tai Nạn Cá Nhân",
    "slug": "huong-dan-bao-hiem-tai-nan-ca-nhan",
    "excerpt": "Hướng dẫn đầy đủ giúp bạn hiểu rõ bảo hiểm tai nạn cá nhân.",
    "content": "<p>Bảo hiểm chi trả chi phí điều trị và bồi thường trong trường hợp thương tật.</p>",
    "published_at": "2024-10-10",
    "author": "Trần Thị K",
    "tags": ["bảo hiểm tai nạn"],
    "thumbnails": [
      "/assets/images/posts/accident1.jpg",
      "/assets/images/posts/accident2.jpg",
      "/assets/images/posts/accident3.jpg",
      "/assets/images/posts/accident4.jpg"
    ],
    "meta": {
      "meta_title": "Hướng Dẫn Về Bảo Hiểm Tai Nạn Cá Nhân - Bảo Vệ Bạn Và Gia Đình",
      "meta_description": "Bài viết giúp bạn nắm rõ quyền lợi và cách thức tham gia bảo hiểm tai nạn cá nhân.",
      "meta_keywords": "bảo hiểm tai nạn, quyền lợi bảo hiểm, bảo hiểm cá nhân"
    }
  },
  {
    "id": 11,
    "title": "Những Điều Cần Biết Về Bảo Hiểm Thất Nghiệp",
    "slug": "nhung-dieu-can-biet-bao-hiem-that-nghiep",
    "excerpt": "Bảo hiểm thất nghiệp hỗ trợ tài chính khi bạn mất việc làm.",
    "content": "<p>Khám phá các điều kiện tham gia và quyền lợi khi hưởng bảo hiểm thất nghiệp.</p>",
    "published_at": "2024-10-11",
    "author": "Nguyễn Văn L",
    "tags": ["bảo hiểm thất nghiệp"],
    "thumbnails": [
      "/assets/images/posts/unemployment1.jpg",
      "/assets/images/posts/unemployment2.jpg",
      "/assets/images/posts/unemployment3.jpg",
      "/assets/images/posts/unemployment4.jpg"
    ],
    "meta": {
      "meta_title": "Thông Tin Về Bảo Hiểm Thất Nghiệp - Hỗ Trợ Tài Chính Hiệu Quả",
      "meta_description": "Tìm hiểu chi tiết quyền lợi và cách thức đăng ký bảo hiểm thất nghiệp.",
      "meta_keywords": "bảo hiểm thất nghiệp, hỗ trợ tài chính, bảo hiểm xã hội"
    }
  },
  {
    "id": 12,
    "title": "Bảo Hiểm Sức Khỏe Cho Người Cao Tuổi",
    "slug": "bao-hiem-suc-khoe-cho-nguoi-cao-tuoi",
    "excerpt": "Giải pháp bảo vệ sức khỏe toàn diện cho người lớn tuổi.",
    "content": "<p>Chọn gói bảo hiểm phù hợp giúp người cao tuổi an tâm chăm sóc sức khỏe.</p>",
    "published_at": "2024-10-12",
    "author": "Trần Thị M",
    "tags": ["bảo hiểm người cao tuổi"],
    "thumbnails": [
      "/assets/images/posts/senior1.jpg",
      "/assets/images/posts/senior2.jpg",
      "/assets/images/posts/senior3.jpg",
      "/assets/images/posts/senior4.jpg"
    ],
    "meta": {
      "meta_title": "Bảo Hiểm Sức Khỏe Cho Người Cao Tuổi - Hướng Dẫn Chi Tiết",
      "meta_description": "Hướng dẫn chọn bảo hiểm sức khỏe tốt nhất dành cho người cao tuổi.",
      "meta_keywords": "bảo hiểm người già, bảo hiểm sức khỏe cao tuổi, chăm sóc sức khỏe"
    }
  }
]
